Metadata-Version: 1.1
Name: RFIMasker
Version: 1.0.1
Summary: Tool to apply rfi masks to measurement sets
Home-page: https://github.com/bennahugo/RFIMasker
Author: Benjamin Hugo
Author-email: bhugo@ska.ac.za
License: GNU GPL v2
Platform: UNKNOWN
Classifier: Development Status :: 3 - Alpha
Classifier: Intended Audience :: Science/Research
Classifier: License :: OSI Approved :: GNU General Public License v2 (GPLv2)
Classifier: Operating System :: OS Independent
Classifier: Programming Language :: Python
Classifier: Topic :: Software Development :: Libraries :: Python Modules
Classifier: Topic :: Scientific/Engineering :: Astronomy
